{"width":2048,"imagePath":"BoostBottle_tex.png","name":"BoostBottle","SubTexture":[{"width":239,"y":1788,"height":133,"name":"WingBoost","x":1101},{"width":76,"y":1374,"height":85,"name":"BottleCapBoost","x":968},{"width":376,"y":814,"height":540,"name":"BottleCrackBoost3","x":968},{"width":601,"y":10,"height":784,"name":"BottleCrackBoost5","x":10},{"width":576,"y":1500,"height":509,"name":"BottleCrackBoost7","x":505},{"width":322,"y":1502,"height":466,"name":"BottleCrackBoost2","x":10},{"width":279,"y":1374,"height":394,"name":"BottleCrackBoost1","x":1101},{"width":475,"y":814,"height":668,"name":"BottleCrackBoost4","x":10},{"width":443,"y":814,"height":666,"name":"BottleCrackBoost6","x":505},{"width":278,"y":10,"height":394,"name":"BottleBoost","x":1364}],"height":2048}